http_clientlib/__init__.py
http_clientlib/api.py
http_clientlib/configuration.py
http_clientlib/http.py
http_clientlib/loggers.py
http_clientlib/parsers.py
http_clientlib/types.py
http_clientlib-0.1.3.dist-info/licenses/LICENSE
http_clientlib-0.1.3.dist-info/METADATA
http_clientlib-0.1.3.dist-info/WHEEL
http_clientlib-0.1.3.dist-info/top_level.txt
http_clientlib-0.1.3.dist-info/RECORD
