Metadata-Version: 2.4
Name: http_clientlib
Version: 0.1.3
Summary: Add your description here
Requires-Python: >=3.11
License-File: LICENSE
Requires-Dist: pydantic>=2.0.0
Requires-Dist: httpx>=0.28.1
Dynamic: license-file
